openapi_client/__init__.py
openapi_client/api_client.py
openapi_client/configuration.py
openapi_client/exceptions.py
openapi_client/model_utils.py
openapi_client/rest.py
openapi_client/api/__init__.py
openapi_client/api/companies_api.py
openapi_client/api/machinecounterreadings_api.py
openapi_client/api/machines_api.py
openapi_client/api/schema_api.py
openapi_client/api/states_api.py
openapi_client/api/telemetry_api.py
openapi_client/apis/__init__.py
openapi_client/model/__init__.py
openapi_client/model/company.py
openapi_client/model/machine.py
openapi_client/model/machine_counter_reading.py
openapi_client/model/machine_state.py
openapi_client/model/telemetry_value.py
openapi_client/models/__init__.py
portal_openapi_client-0.2.5.dist-info/METADATA
portal_openapi_client-0.2.5.dist-info/WHEEL
portal_openapi_client-0.2.5.dist-info/top_level.txt
portal_openapi_client-0.2.5.dist-info/RECORD
